MANIFEST.in
README.rst
setup.py
google_trans/__init__.py
google_trans/adapters.py
google_trans/client.py
google_trans/compat.py
google_trans/constants.py
google_trans/gtoken.py
google_trans/models.py
google_trans/urls.py
google_trans/utils.py
google_trans.egg-info/PKG-INFO
google_trans.egg-info/SOURCES.txt
google_trans.egg-info/dependency_links.txt
google_trans.egg-info/top_level.txt